lattice_cryptography/__init__.py
lattice_cryptography/adaptor_sigs.py
lattice_cryptography/bklm_one_time_agg_sigs.py
lattice_cryptography/lm_one_time_sigs.py
lattice_cryptography/one_time_keys.py
lattice_cryptography-0.0.3.dist-info/LICENSE
lattice_cryptography-0.0.3.dist-info/METADATA
lattice_cryptography-0.0.3.dist-info/WHEEL
lattice_cryptography-0.0.3.dist-info/top_level.txt
lattice_cryptography-0.0.3.dist-info/RECORD
